[
    {
        "image": "other-default.png",
        "location": "Lansing, MI, United States",
        "date": "Mar 14, 2026",
        "url": "https://www.ifpapinball.com/tournaments/view.php?t=109959",
        "title": "Lansing Lightning Rater",
        "status": "past",
        "id": 0,
        "facebook_url": "",
        "website": "https://www.lansingpinleague.com/lansing-lightning-flippers/",
        "description": "Address\n                                                                                            2021 E. Michigan Ave.\nLansing, MI 48912\n                                                                                    \n                                    \n                                    \n                                        \n                                            \n                                            Registration Opens\n                                                                                            Day of Tournament\n                                                                                    \n                                    \n                                    \n                                        \n                                            \n                                                                                            Qualifying Format\n                                                Best Game\n                                                                                    \n                                    \n                                \n\n                                \n                                    \n                                        \n                                            \n                                            Player Limit\n                                                                                            No Limit\n                                                                                    \n                                    \n                                    \n                                        \n                                            \n                                            Registration Fee\n                                                                                            Check Tournament Website\n                                                                                    \n                                    \n                                                                        \n                                        \n                                            \n                                            Finals Format\n                                            Match Play",
        "start_time": "Check Tournament Website",
        "event_name": "Side Tournament",
        "address": "2021 E. Michigan Ave.\nLansing, MI 48912",
        "director": "Heather Kendrick",
        "ranking_system": "Women",
        "registration_opens": "Day of Tournament",
        "qualifying_format": "Best Game",
        "player_limit": "No Limit",
        "registration_fee": "Check Tournament Website",
        "finals_format": "Match Play"
    },
    {
        "image": "images/mi_event_1.jpg",
        "location": "Detroit, MI, United States",
        "date": "Mar 11, 2026",
        "url": "https://www.ifpapinball.com/tournaments/view.php?t=107945",
        "title": "Belles 2nd Wednesdays @ Barcade",
        "status": "past",
        "id": 1,
        "facebook_url": "https://www.facebook.com/share/17RjsnS8KU/",
        "website": "",
        "description": "Address\n                                                                                            666 Selden St\nDetroit, MI\n                                    \n                                                                                    \n                                    \n                                    \n                                        \n                                            \n                                            Registration Opens\n                                                                                            Day of Tournament\n                                                                                    \n                                    \n                                    \n                                        \n                                            \n                                                                                            Qualifying Format\n                                                Matchplay Qualifying\n                                                                                    \n                                    \n                                \n\n                                \n                                    \n                                        \n                                            \n                                            Player Limit\n                                                                                            No Limit\n                                                                                    \n                                    \n                                    \n                                        \n                                            \n                                            Registration Fee\n                                                                                            Check Tournament Website\n                                                                                    \n                                    \n                                                                        \n                                        \n                                            \n                                            Finals Format\n                                            Single Elimination",
        "start_time": "Check Tournament Website",
        "event_name": "Womens Division",
        "address": "666 Selden St\nDetroit, MI",
        "director": "Bellesandchimes Detroit",
        "ranking_system": "Women",
        "registration_opens": "Day of Tournament",
        "qualifying_format": "Matchplay Qualifying",
        "player_limit": "No Limit",
        "registration_fee": "Check Tournament Website",
        "finals_format": "Single Elimination"
    }
]